{
  "id": "21",
  "province": "KEPULAUAN RIAU",
  "city": [
    {
      "id": "21.01",
      "name": "KAB. BINTAN"
    },
    {
      "id": "21.02",
      "name": "KAB. KARIMUN"
    },
    {
      "id": "21.03",
      "name": "KAB. NATUNA"
    },
    {
      "id": "21.04",
      "name": "KAB. LINGGA"
    },
    {
      "id": "21.05",
      "name": "KAB. KEPULAUAN ANAMBAS"
    },
    {
      "id": "21.71",
      "name": "KOTA BATAM"
    },
    {
      "id": "21.72",
      "name": "KOTA TANJUNG PINANG"
    }
  ]
}