[
  {
    "id": "91.09.12.2005",
    "name": "Akar"
  },
  {
    "id": "91.09.12.2001",
    "name": "Kapiraya"
  },
  {
    "id": "91.09.12.2007",
    "name": "Kipia"
  },
  {
    "id": "91.09.12.2006",
    "name": "Mapar"
  },
  {
    "id": "91.09.12.2003",
    "name": "Mupuruka"
  },
  {
    "id": "91.09.12.2008",
    "name": "Pronggo"
  },
  {
    "id": "91.09.12.2002",
    "name": "Uta"
  },
  {
    "id": "91.09.12.2009",
    "name": "Wakia"
  },
  {
    "id": "91.09.12.2004",
    "name": "Wumuka"
  }
]