[
  {
    "id": "91.07.19.2004",
    "name": "Anggutari"
  },
  {
    "id": "91.07.19.2006",
    "name": "Dondo"
  },
  {
    "id": "91.07.19.2002",
    "name": "Jiginikime"
  },
  {
    "id": "91.07.19.2008",
    "name": "Niruwi"
  },
  {
    "id": "91.07.19.2003",
    "name": "Puncak Senyum"
  },
  {
    "id": "91.07.19.2007",
    "name": "Tanoba"
  },
  {
    "id": "91.07.19.2001",
    "name": "Wondenggobak"
  },
  {
    "id": "91.07.19.2005",
    "name": "Wunagelo"
  },
  {
    "id": "91.07.19.2009",
    "name": "Yalikambi"
  }
]