[
  {
    "id": "92.10.05.2001",
    "name": "Kambufatem"
  },
  {
    "id": "92.10.05.2002",
    "name": "Kambufatem Utara"
  },
  {
    "id": "92.10.05.2003",
    "name": "Fatase"
  },
  {
    "id": "92.10.05.2008",
    "name": "Hosyo Ata"
  },
  {
    "id": "92.10.05.2009",
    "name": "Waybomatah"
  },
  {
    "id": "92.10.05.2010",
    "name": "Siyo"
  },
  {
    "id": "92.10.05.2011",
    "name": "Hasweh"
  },
  {
    "id": "92.10.05.2012",
    "name": "Fatem"
  },
  {
    "id": "92.10.05.2013",
    "name": "Hosyo Banah"
  }
]