[
  {
    "id": "92.05.24",
    "name": "Ayau"
  },
  {
    "id": "92.05.25",
    "name": "Batanta Selatan"
  },
  {
    "id": "92.05.20",
    "name": "Batanta Utara"
  },
  {
    "id": "92.05.05",
    "name": "Kepulauan Ayau"
  },
  {
    "id": "92.05.17",
    "name": "Kepulauan Sembilan"
  },
  {
    "id": "92.05.10",
    "name": "Kofiau"
  },
  {
    "id": "92.05.18",
    "name": "Kota Waisai"
  },
  {
    "id": "92.05.11",
    "name": "Meos Mansar"
  },
  {
    "id": "92.05.01",
    "name": "Misool (Misool Utara)"
  },
  {
    "id": "92.05.16",
    "name": "Misool Barat"
  },
  {
    "id": "92.05.13",
    "name": "Misool Selatan"
  },
  {
    "id": "92.05.06",
    "name": "Misool Timur"
  },
  {
    "id": "92.05.21",
    "name": "Salawati Barat"
  },
  {
    "id": "92.05.22",
    "name": "Salawati Tengah"
  },
  {
    "id": "92.05.04",
    "name": "Salawati Utara"
  },
  {
    "id": "92.05.23",
    "name": "Supnin"
  },
  {
    "id": "92.05.09",
    "name": "Teluk Mayalibit"
  },
  {
    "id": "92.05.19",
    "name": "Tiplol Mayalibit"
  },
  {
    "id": "92.05.07",
    "name": "Waigeo Barat"
  },
  {
    "id": "92.05.15",
    "name": "Waigeo Barat Kepulauan"
  },
  {
    "id": "92.05.03",
    "name": "Waigeo Selatan"
  },
  {
    "id": "92.05.08",
    "name": "Waigeo Timur"
  },
  {
    "id": "92.05.02",
    "name": "Waigeo Utara"
  },
  {
    "id": "92.05.14",
    "name": "Warwarbomi"
  }
]